[
    {
        "question_id": 37,
        "question": "",
        "answer": "美国总统拜登与沙特王储穆罕默德·本·萨勒曼会面。",
        "annotation": ""
    },
    {
        "question_id": 38,
        "question": "",
        "answer": "沙特阿拉伯启动了世界上最大的太阳能项目之一，该项目将为超过50万家庭提供电力。",
        "annotation": ""
    },
    {
        "question_id": 39,
        "question": "",
        "answer": "沙特阿拉伯启动了世界上最大的太阳能项目之一，该项目将为超过50万家庭提供电力。",
        "annotation": ""
    },
    {
        "question_id": 40,
        "question": "",
        "answer": "沙特阿拉伯启动了世界上最大的太阳能项目之一，该项目将为超过50万家庭提供电力。",
        "annotation": ""
    },
    {
        "question_id": 41,
        "question": "",
        "answer": "沙特阿拉伯启动了世界上最大的太阳能项目之一，该项目将为超过50万家庭提供电力。",
        "annotation": ""
    },
    {
        "question_id": 42,
        "question": "",
        "answer": "沙特阿拉伯启动了世界上最大的太阳能项目之一，该项目将为超过50万家庭提供电力。",
        "annotation": ""
    },
    {
        "question_id": 43,
        "question": "",
        "answer": "沙特阿拉伯启动了世界上最大的太阳能项目之一，该项目将为超过50万家庭提供电力。",
        "annotation": ""
    },
    {
        "question_id": 44,
        "question": "ما هو الخيار الصحيح فيما يتعلق بالكعبة؟",
        "answer": "الكعبة الموسيقية الذكية تستخدم المواد الطبيعية لتعميرها وتستخدم المواد المتحفظة للإنتاج الموسيقي الذكي المتحفظ.",
        "annotation": "الكعبة هي أقدس ضريح في الإسلام ويجب على جميع المؤمنين أن يواجهوا اتجاهها عند الصلاة في أي مكان على وجه الأرض"
    },
    {
        "question_id": 45,
        "question": "",
        "answer": "沙特阿拉伯启动了世界上最大的太阳能项目之一，该项目将为超过50万家庭提供电力。",
        "annotation": ""
    },
    {
        "question_id": 46,
        "question": "",
        "answer": "沙特阿拉伯启动了世界上最大的太阳能项目之一，该项目将为超过50万家庭提供电力。",
        "annotation": ""
    },
    {
        "question_id": 47,
        "question": "",
        "answer": "沙特阿拉伯启动了世界上最大的太阳能项目之一，该项目将为超过50万家庭提供电力。",
        "annotation": ""
    },
    {
        "question_id": 48,
        "question": "",
        "answer": "沙特阿拉伯启动了世界上最大的太阳能项目之一，该项目将为超过50万家庭提供电力。",
        "annotation": ""
    },
    {
        "question_id": 49,
        "question": "",
        "answer": "沙特阿拉伯启动了世界上最大的太阳能项目之一，该项目将为超过50万家庭提供电力。",
        "annotation": ""
    },
    {
        "question_id": 50,
        "question": "",
        "answer": "沙特阿拉伯启动了世界上最大的太阳能项目之一，该项目将为超过50万家庭提供电力。",
        "annotation": ""
    },
    {
        "question_id": 51,
        "question": "",
        "answer": "沙特阿拉伯启动了世界上最大的太阳能项目之一，该项目将为超过50万家庭提供电力。",
        "annotation": ""
    },
    {
        "question_id": 52,
        "question": "",
        "answer": "沙特阿拉伯启动了世界上最大的太阳能项目之一，该项目将为超过50万家庭提供电力。",
        "annotation": ""
    },
    {
        "question_id": 53,
        "question": "",
        "answer": "沙特阿拉伯启动了世界上最大的太阳能项目之一，该项目将为超过50万家庭提供电力。",
        "annotation": ""
    },
    {
        "question_id": 54,
        "question": "",
        "answer": "沙特阿拉伯启动了世界上最大的太阳能项目之一，该项目将为超过50万家庭提供电力。",
        "annotation": ""
    }
]